logging_midlleware/__init__.py
logging_midlleware/fastapi_midlleware.py
logging_midlleware/faststream_midlleware.py
logging_midlleware/graylog.py
logging_midlleware/py.typed
logging_midlleware-0.6.0.dist-info/METADATA
logging_midlleware-0.6.0.dist-info/WHEEL
logging_midlleware-0.6.0.dist-info/entry_points.txt
logging_midlleware-0.6.0.dist-info/RECORD
