Metadata-Version: 2.4
Name: logging-midlleware
Version: 0.6.0
Summary: Add your description here
Author-email: shadrin-vi <kod3852@gmail.com>
Requires-Python: >=3.10
Requires-Dist: amqp>=5.3.1
Requires-Dist: faststream>=0.5.43
Requires-Dist: graypy>=2.1.0
Requires-Dist: starlette>=0.37.2
